themefinder/__init__.py
themefinder/advanced_tasks/__init__.py
themefinder/advanced_tasks/cross_cutting_themes_agent.py
themefinder/advanced_tasks/theme_clustering_agent.py
themefinder/llm_batch_processor.py
themefinder/models.py
themefinder/prompts/agentic_theme_clustering.txt
themefinder/prompts/consultation_system_prompt.txt
themefinder/prompts/cross_cutting_identification.txt
themefinder/prompts/cross_cutting_mapping.txt
themefinder/prompts/cross_cutting_refinement.txt
themefinder/prompts/detail_detection.txt
themefinder/prompts/sentiment_analysis.txt
themefinder/prompts/theme_condensation.txt
themefinder/prompts/theme_generation.txt
themefinder/prompts/theme_mapping.txt
themefinder/prompts/theme_refinement.txt
themefinder/prompts/theme_target_alignment.txt
themefinder/tasks.py
themefinder/themefinder_logging.py
themefinder-0.7.7.dist-info/METADATA
themefinder-0.7.7.dist-info/WHEEL
themefinder-0.7.7.dist-info/licenses/LICENCE
themefinder-0.7.7.dist-info/RECORD
