Metadata-Version: 2.4
Name: themefinder
Version: 0.7.7
Summary: A topic modelling Python package designed for analysing one-to-many question-answer data eg free-text survey responses.
License: MIT
License-File: LICENCE
Author: i.AI
Author-email: packages@cabinetoffice.gov.uk
Requires-Python: >=3.10,<3.13
Classifier: Intended Audience :: Developers
Classifier: Intended Audience :: Science/Research
Classifier: License :: OSI Approved :: MIT License
Classifier: Programming Language :: Python :: 3
Classifier: Programming Language :: Python :: 3.10
Classifier: Programming Language :: Python :: 3.11
Classifier: Programming Language :: Python :: 3.12
Classifier: Topic :: Scientific/Engineering :: Artificial Intelligence
Classifier: Topic :: Text Processing :: Linguistic
Requires-Dist: boto3 (>=1.29,<2.0)
Requires-Dist: langchain
Requires-Dist: langchain-openai
Requires-Dist: langfuse (==2.29.1)
Requires-Dist: openpyxl (>=3.1.5,<4.0.0)
Requires-Dist: pandas (>=2.2.2,<3.0.0)
Requires-Dist: pyarrow (>=15.0.0,<16.0.0)
Requires-Dist: python-dotenv (>=1.0.1,<2.0.0)
Requires-Dist: scikit-learn
Requires-Dist: toml (>=0.10.2,<0.11.0)
Project-URL: Documentation, https://i-dot-ai.github.io/themefinder/
Project-URL: Repository, https://github.com/i-dot-ai/themefinder/
